mouse_book_2_client-0.1.0.dist-info/METADATA
mouse_book_2_client-0.1.0.dist-info/WHEEL
mouse_book_2_client/__init__.py
mouse_book_2_client/client.py
mouse_book_2_client/integrations.py
mouse_book_2_client/schemas.py
mouse_book_2_client-0.1.0.dist-info/RECORD
