Metadata-Version: 2.1
Name: mouse-book-2-client
Version: 0.1.0
Author-Email: Christopher Mochizuki <mochic808@gmail.com>
License: MIT
Requires-Python: >=3.9
Requires-Dist: requests>=2.31.0
Requires-Dist: pydantic>=2.1.1
